{
"meta":{"test_sets":[],"test_metrics":[],"learn_metrics":[{"best_value":"Min","name":"Logloss"}],"launch_mode":"Train","parameters":"","iteration_count":100,"learn_sets":["learn"],"name":"experiment"},
"iterations":[
{"learn":[0.5640422909],"iteration":0,"passed_time":0.01584804186,"remaining_time":1.568956144},
{"learn":[0.437470734],"iteration":1,"passed_time":0.03171869475,"remaining_time":1.554216043},
{"learn":[0.3800747628],"iteration":2,"passed_time":0.04748687207,"remaining_time":1.535408864},
{"learn":[0.3319843782],"iteration":3,"passed_time":0.06281651499,"remaining_time":1.50759636},
{"learn":[0.3008222273],"iteration":4,"passed_time":0.07786537534,"remaining_time":1.479442131},
{"learn":[0.272815128],"iteration":5,"passed_time":0.09482641461,"remaining_time":1.485613829},
{"learn":[0.2349499008],"iteration":6,"passed_time":0.120149313,"remaining_time":1.596269444},
{"learn":[0.2208938225],"iteration":7,"passed_time":0.1368736056,"remaining_time":1.574046465},
{"learn":[0.2103964522],"iteration":8,"passed_time":0.1689095871,"remaining_time":1.707863603},
{"learn":[0.2026793429],"iteration":9,"passed_time":0.1838558056,"remaining_time":1.65470225},
{"learn":[0.1937040828],"iteration":10,"passed_time":0.1986032682,"remaining_time":1.606880988},
{"learn":[0.1857757668],"iteration":11,"passed_time":0.2154776749,"remaining_time":1.580169616},
{"learn":[0.1800620935],"iteration":12,"passed_time":0.229181642,"remaining_time":1.533754066},
{"learn":[0.1754381011],"iteration":13,"passed_time":0.2453435315,"remaining_time":1.507110265},
{"learn":[0.1722591154],"iteration":14,"passed_time":0.2606189556,"remaining_time":1.476840748},
{"learn":[0.1686932122],"iteration":15,"passed_time":0.2758509185,"remaining_time":1.448217322},
{"learn":[0.1631090702],"iteration":16,"passed_time":0.2913872766,"remaining_time":1.422655527},
{"learn":[0.1607858596],"iteration":17,"passed_time":0.30721571,"remaining_time":1.399538235},
{"learn":[0.158507877],"iteration":18,"passed_time":0.3240460408,"remaining_time":1.381459437},
{"learn":[0.1560862881],"iteration":19,"passed_time":0.3388656971,"remaining_time":1.355462788},
{"learn":[0.1535751208],"iteration":20,"passed_time":0.3555249801,"remaining_time":1.337451116},
{"learn":[0.1507324912],"iteration":21,"passed_time":0.3700998415,"remaining_time":1.312172165},
{"learn":[0.1490127823],"iteration":22,"passed_time":0.3898885084,"remaining_time":1.305278919},
{"learn":[0.1453049505],"iteration":23,"passed_time":0.4036919185,"remaining_time":1.278357742},
{"learn":[0.1436351688],"iteration":24,"passed_time":0.4213342999,"remaining_time":1.2640029},
{"learn":[0.1425102309],"iteration":25,"passed_time":0.4378689634,"remaining_time":1.246242434},
{"learn":[0.140889454],"iteration":26,"passed_time":0.4516858881,"remaining_time":1.221224809},
{"learn":[0.1394783086],"iteration":27,"passed_time":0.4658593288,"remaining_time":1.197923988},
{"learn":[0.1379493674],"iteration":28,"passed_time":0.4830494959,"remaining_time":1.182638421},
{"learn":[0.1365868428],"iteration":29,"passed_time":0.5233646842,"remaining_time":1.221184263},
{"learn":[0.1352705014],"iteration":30,"passed_time":0.5549258083,"remaining_time":1.235157444},
{"learn":[0.1345008758],"iteration":31,"passed_time":0.5743373257,"remaining_time":1.220466817},
{"learn":[0.1327012685],"iteration":32,"passed_time":0.5945085177,"remaining_time":1.207032445},
{"learn":[0.1318496938],"iteration":33,"passed_time":0.6119342059,"remaining_time":1.187872282},
{"learn":[0.131302344],"iteration":34,"passed_time":0.6346439083,"remaining_time":1.178624401},
{"learn":[0.13049898],"iteration":35,"passed_time":0.6520648616,"remaining_time":1.159226421},
{"learn":[0.129178968],"iteration":36,"passed_time":0.6788900077,"remaining_time":1.155947851},
{"learn":[0.1280205313],"iteration":37,"passed_time":0.6950097839,"remaining_time":1.133963332},
{"learn":[0.1270757279],"iteration":38,"passed_time":0.7090910575,"remaining_time":1.109091141},
{"learn":[0.1252130141],"iteration":39,"passed_time":0.7246917662,"remaining_time":1.087037649},
{"learn":[0.1233626824],"iteration":40,"passed_time":0.7420025552,"remaining_time":1.067759775},
{"learn":[0.1228628283],"iteration":41,"passed_time":0.7569630604,"remaining_time":1.045329941},
{"learn":[0.1224562877],"iteration":42,"passed_time":0.7717382877,"remaining_time":1.023001916},
{"learn":[0.1202170395],"iteration":43,"passed_time":0.786257798,"remaining_time":1.000691743},
{"learn":[0.1197077908],"iteration":44,"passed_time":0.8021988222,"remaining_time":0.9804652271},
{"learn":[0.1189585106],"iteration":45,"passed_time":0.8167397859,"remaining_time":0.9587814878},
{"learn":[0.1181537964],"iteration":46,"passed_time":0.8309809921,"remaining_time":0.937063672},
{"learn":[0.1168501478],"iteration":47,"passed_time":0.8502496337,"remaining_time":0.9211037699},
{"learn":[0.1163293295],"iteration":48,"passed_time":0.8658823377,"remaining_time":0.9012244739},
{"learn":[0.1154974944],"iteration":49,"passed_time":0.8819882243,"remaining_time":0.8819882243},
{"learn":[0.115169855],"iteration":50,"passed_time":0.8962670483,"remaining_time":0.8611193209},
{"learn":[0.114769808],"iteration":51,"passed_time":0.9115474332,"remaining_time":0.8414283999},
{"learn":[0.1124623015],"iteration":52,"passed_time":0.9272528397,"remaining_time":0.8222808201},
{"learn":[0.111928563],"iteration":53,"passed_time":0.9449056151,"remaining_time":0.804919598},
{"learn":[0.1113655438],"iteration":54,"passed_time":0.9597683699,"remaining_time":0.7852650299},
{"learn":[0.1110614511],"iteration":55,"passed_time":0.9738952561,"remaining_time":0.7652034155},
{"learn":[0.1102571092],"iteration":56,"passed_time":0.9883043352,"remaining_time":0.7455629196},
{"learn":[0.1097885038],"iteration":57,"passed_time":1.001651129,"remaining_time":0.7253335762},
{"learn":[0.1094868392],"iteration":58,"passed_time":1.016294373,"remaining_time":0.7062384625},
{"learn":[0.1092356104],"iteration":59,"passed_time":1.029303605,"remaining_time":0.6862024033},
{"learn":[0.1090122558],"iteration":60,"passed_time":1.046164159,"remaining_time":0.6688590527},
{"learn":[0.1085214115],"iteration":61,"passed_time":1.059789778,"remaining_time":0.6495485734},
{"learn":[0.1081841609],"iteration":62,"passed_time":1.076335052,"remaining_time":0.6321332842},
{"learn":[0.1078558886],"iteration":63,"passed_time":1.091242643,"remaining_time":0.6138239865},
{"learn":[0.1075700926],"iteration":64,"passed_time":1.107767119,"remaining_time":0.5964899871},
{"learn":[0.1067227667],"iteration":65,"passed_time":1.129410809,"remaining_time":0.5818176893},
{"learn":[0.1058453808],"iteration":66,"passed_time":1.148107876,"remaining_time":0.565485969},
{"learn":[0.1054341857],"iteration":67,"passed_time":1.173272177,"remaining_time":0.5521280831},
{"learn":[0.1051330005],"iteration":68,"passed_time":1.189529843,"remaining_time":0.5344264511},
{"learn":[0.1048520113],"iteration":69,"passed_time":1.203163031,"remaining_time":0.5156412989},
{"learn":[0.1044242415],"iteration":70,"passed_time":1.220871675,"remaining_time":0.4986658956},
{"learn":[0.1038689194],"iteration":71,"passed_time":1.237197354,"remaining_time":0.4811323044},
{"learn":[0.1036437882],"iteration":72,"passed_time":1.251337138,"remaining_time":0.4628233251},
{"learn":[0.1032084304],"iteration":73,"passed_time":1.266169224,"remaining_time":0.4448702679},
{"learn":[0.1027352354],"iteration":74,"passed_time":1.283085675,"remaining_time":0.4276952249},
{"learn":[0.1025615658],"iteration":75,"passed_time":1.296934478,"remaining_time":0.4095582563},
{"learn":[0.1021161203],"iteration":76,"passed_time":1.311359329,"remaining_time":0.3917047348},
{"learn":[0.1016463976],"iteration":77,"passed_time":1.327008437,"remaining_time":0.3742844311},
{"learn":[0.1013720729],"iteration":78,"passed_time":1.34086555,"remaining_time":0.3564326144},
{"learn":[0.1011470683],"iteration":79,"passed_time":1.357721137,"remaining_time":0.3394302843},
{"learn":[0.1010068637],"iteration":80,"passed_time":1.369274342,"remaining_time":0.3211878087},
{"learn":[0.1007250271],"iteration":81,"passed_time":1.386699984,"remaining_time":0.3043975575},
{"learn":[0.1005451641],"iteration":82,"passed_time":1.402553225,"remaining_time":0.2872699377},
{"learn":[0.1004372543],"iteration":83,"passed_time":1.417148064,"remaining_time":0.2699329645},
{"learn":[0.100287646],"iteration":84,"passed_time":1.432292655,"remaining_time":0.2527575273},
{"learn":[0.1000315495],"iteration":85,"passed_time":1.45015251,"remaining_time":0.2360713388},
{"learn":[0.09996002882],"iteration":86,"passed_time":1.464252806,"remaining_time":0.2187963963},
{"learn":[0.09967691969],"iteration":87,"passed_time":1.480800792,"remaining_time":0.2019273807},
{"learn":[0.09956322331],"iteration":88,"passed_time":1.497254697,"remaining_time":0.1850539513},
{"learn":[0.09937907867],"iteration":89,"passed_time":1.514250311,"remaining_time":0.1682500346},
{"learn":[0.09929406673],"iteration":90,"passed_time":1.530324885,"remaining_time":0.1513508128},
{"learn":[0.09897845132],"iteration":91,"passed_time":1.545704991,"remaining_time":0.1344091296},
{"learn":[0.09887960344],"iteration":92,"passed_time":1.559922315,"remaining_time":0.1174135076},
{"learn":[0.09855602245],"iteration":93,"passed_time":1.575613883,"remaining_time":0.1005710989},
{"learn":[0.09843133087],"iteration":94,"passed_time":1.591662417,"remaining_time":0.08377170616},
{"learn":[0.09825557496],"iteration":95,"passed_time":1.6085742,"remaining_time":0.06702392499},
{"learn":[0.09802491542],"iteration":96,"passed_time":1.624461668,"remaining_time":0.05024108251},
{"learn":[0.0974860944],"iteration":97,"passed_time":1.639001131,"remaining_time":0.03344900268},
{"learn":[0.09736028717],"iteration":98,"passed_time":1.654548856,"remaining_time":0.01671261471},
{"learn":[0.09728981834],"iteration":99,"passed_time":1.669322379,"remaining_time":0}
]}